clustar/__init__.py
clustar/base.py
clustar/core.py
clustar/denoise.py
clustar/fit.py
clustar/graph.py
clustar/group.py
clustar/search.py
tests/__init__.py
tests/test_denoise.py
clustar-1.2.1.dist-info/LICENSE.txt
clustar-1.2.1.dist-info/METADATA
clustar-1.2.1.dist-info/WHEEL
clustar-1.2.1.dist-info/top_level.txt
clustar-1.2.1.dist-info/RECORD
