Metadata-Version: 2.1
Name: clustar
Version: 1.2.1
Summary: A python package for processing and analyzing protostars/
Home-page: https://github.com/clustar/clustar
Author: Pavan Kumar Bondalapati
Author-email: pb7ak@virginia.edu
License: UNKNOWN
Keywords: cluster,astronomy,protostars
Platform: UNKNOWN
Classifier: Development Status :: 3 - Alpha
Classifier: Intended Audience :: Developers
Classifier: Topic :: Software Development :: Build Tools
Classifier: License :: OSI Approved :: MIT License
Classifier: Programming Language :: Python :: 3
Classifier: Programming Language :: Python :: 3.6
Classifier: Programming Language :: Python :: 3.7
Classifier: Programming Language :: Python :: 3.8
Classifier: Programming Language :: Python :: 3.9
Classifier: Programming Language :: Python :: 3 :: Only
Requires-Python: >=3.6, <4
Requires-Dist: numpy (~=1.20.1)
Requires-Dist: scipy (~=1.6.1)
Requires-Dist: astropy (~=4.2)
Requires-Dist: matplotlib (~=3.3.4)
Requires-Dist: pandas (~=1.2.3)
Requires-Dist: tqdm (~=4.50.2)
Provides-Extra: dev
Requires-Dist: pytest (>=5.4.1) ; extra == 'dev'
